shufflish/__init__.py
shufflish/_affine.cpython-311-x86_64-linux-gnu.so
shufflish/_version.py
shufflish-0.1.0.dist-info/METADATA
shufflish-0.1.0.dist-info/WHEEL
shufflish-0.1.0.dist-info/top_level.txt
shufflish-0.1.0.dist-info/RECORD
shufflish-0.1.0.dist-info/licenses/LICENSE
