Metadata-Version: 2.4
Name: shufflish
Version: 0.1.0
Summary: For when you need to kind of shuffle lots of integers.
Author-email: Joachim Folz <joachim.folz@dfki.de>
License-Expression: MIT
Project-URL: Homepage, https://github.com/jfolz/shufflish
Project-URL: Documentation, https://shufflish.readthedocs.io/stable/
Project-URL: Repository, https://github.com/jfolz/shufflish
Project-URL: Issues, https://github.com/jfolz/shufflish/issues
Project-URL: Changelog, https://github.com/jfolz/shufflish/blob/main/CHANGELOG.md
Keywords: shuffle,shuffling,permutation,random,rng,affine,cipher,affine cipher
Classifier: Development Status :: 3 - Alpha
Classifier: Intended Audience :: Developers
Classifier: Intended Audience :: Science/Research
Classifier: Intended Audience :: Information Technology
Classifier: Intended Audience :: Other Audience
Classifier: Programming Language :: Python :: Implementation :: CPython
Classifier: Programming Language :: Python :: 3.9
Classifier: Programming Language :: Python :: 3.10
Classifier: Programming Language :: Python :: 3.11
Classifier: Programming Language :: Python :: 3.12
Classifier: Programming Language :: Python :: 3.13
Classifier: Programming Language :: Python :: 3.14
Requires-Python: >=3.9
License-File: LICENSE
Dynamic: license-file
